AUTHORS
LICENSE
MANIFEST.in
README.rst
setup.py
bin/hourglass
hourglass/__init__.py
hourglass/clock.py
hourglass/job.py
hourglass/schedule.py
hourglass/version.py
hourglass.egg-info/PKG-INFO
hourglass.egg-info/SOURCES.txt
hourglass.egg-info/dependency_links.txt
hourglass.egg-info/requires.txt
hourglass.egg-info/top_level.txt