Metadata-Version: 1.0
Name: hourglass
Version: 0.1.2
Summary: Scheduling for rq.
Home-page: http://github.com/pitchfork/hourglass/
Author: Pitchfork Media, Inc.
Author-email: dev@pitchfork.com
License: UNKNOWN
Platform: UNKNOWN
Classifier: Development Status :: 5 - Production/Stable
Classifier: Intended Audience :: Developers
Classifier: License :: OSI Approved :: BSD License
Classifier: Programming Language :: Python
